wombatoo/DataCard.txt
wombatoo/__init__.py
wombatoo/wombatoo.py
wombatoo-1.0.0.dist-info/LICENSE.md
wombatoo-1.0.0.dist-info/METADATA
wombatoo-1.0.0.dist-info/WHEEL
wombatoo-1.0.0.dist-info/top_level.txt
wombatoo-1.0.0.dist-info/RECORD
