Metadata-Version: 2.1
Name: wombatoo
Version: 1.0.0
Summary: A Data-Ops tool for devs
Author-email: Prashant Singh <prashdash112@gmail.com>
Project-URL: Homepage, https://github.com/prashdash112/wombatoo
Project-URL: Bug Tracker, https://github.com/prashdash112/wombatoo/issues
Requires-Python: >=3.6
License-File: LICENSE.md
Requires-Dist: numpy (==1.23.5)
Requires-Dist: pandas (==1.5.2)
Requires-Dist: pyhtml2pdf (==0.0.6)
Requires-Dist: ydata-profiling (==4.1.1)
